sigmond_scripts/__init__.py
sigmond_scripts/channel.py
sigmond_scripts/correlator_data.py
sigmond_scripts/data_files.py
sigmond_scripts/data_handler.py
sigmond_scripts/fit_info.py
sigmond_scripts/isospin.py
sigmond_scripts/operator.py
sigmond_scripts/operator_set.py
sigmond_scripts/sigmond_info.py
sigmond_scripts/sigmond_input.py
sigmond_scripts/sigmond_log.py
sigmond_scripts/util.py
sigmond_scripts/analysis/__init__.py
sigmond_scripts/analysis/launcher.py
sigmond_scripts/analysis/run_sigmond.py
sigmond_scripts/analysis/operator_info/__init__.py
sigmond_scripts/analysis/sigmond_info/__init__.py
sigmond_scripts/analysis/utils/__init__.py
sigmond_scripts/analysis/utils/menu.py
sigmond_scripts/analysis/utils/plotting.py
sigmond_scripts-1.0.2.dist-info/LICENSE
sigmond_scripts-1.0.2.dist-info/METADATA
sigmond_scripts-1.0.2.dist-info/WHEEL
sigmond_scripts-1.0.2.dist-info/top_level.txt
sigmond_scripts-1.0.2.dist-info/RECORD
