Metadata-Version: 2.1
Name: sigmond_scripts
Version: 1.0.2
Summary: Supporting functions for handling the c++ library sigmond
Author: Drew Hanlon
Author-email: ahanlon@bnl.gov
Classifier: Programming Language :: Python :: 3
Classifier: License :: OSI Approved :: MIT License
Classifier: Operating System :: OS Independent
Requires-Python: >=3.6
License-File: LICENSE
Requires-Dist: numpy
Requires-Dist: regex
Requires-Dist: pylatex
Requires-Dist: uncertainties
Requires-Dist: h5py
Requires-Dist: sortedcontainers
Requires-Dist: tqdm
Requires-Dist: aenum
